pdf2image_cli/__init__.py
pdf2image_cli/__main__.py
pdf2image_cli/core.py
pdf2image_cli/spinner.py
pdf2image_cli/status.py
pdf2image_cli-1.0.0.dist-info/LICENSE
pdf2image_cli-1.0.0.dist-info/METADATA
pdf2image_cli-1.0.0.dist-info/WHEEL
pdf2image_cli-1.0.0.dist-info/entry_points.txt
pdf2image_cli-1.0.0.dist-info/top_level.txt
pdf2image_cli-1.0.0.dist-info/RECORD
