Metadata-Version: 2.1
Name: pdf2image-cli
Version: 1.0.0
Summary: pdf2image port to a CLI version
Home-page: https://github.com/DJCarlosValdez/pdf2image-cli
Author: Carlos Valdez
Author-email: carlosvaldez@carlosvaldez.works
License: UNKNOWN
Platform: UNKNOWN
Requires-Python: >=3.8
License-File: LICENSE
Requires-Dist: pip
Requires-Dist: setuptools
Requires-Dist: pdf2image (>=1.16.0)
